Metadata-Version: 2.1
Name: wizata-demo-scripts
Version: 0.0.1
Summary: Scripts to make Wizata demos.
Home-page: https://github.com/albertcdc/Wizata_demos
Author: aco
